tinyshare/__init__.py
tinyshare/py310/__init__.pyc
tinyshare/py310/cache_utils.pyc
tinyshare/py310/cert_utils.pyc
tinyshare/py310/common_permission.pyc
tinyshare/py310/config.pyc
tinyshare/py310/device_id.pyc
tinyshare/py310/formula.pyc
tinyshare/py310/general_api_wrapper.pyc
tinyshare/py310/token_utils.pyc
tinyshare/py311/__init__.pyc
tinyshare/py311/cache_utils.pyc
tinyshare/py311/cert_utils.pyc
tinyshare/py311/common_permission.pyc
tinyshare/py311/config.pyc
tinyshare/py311/device_id.pyc
tinyshare/py311/formula.pyc
tinyshare/py311/general_api_wrapper.pyc
tinyshare/py311/token_utils.pyc
tinyshare/py312/__init__.pyc
tinyshare/py312/cache_utils.pyc
tinyshare/py312/cert_utils.pyc
tinyshare/py312/common_permission.pyc
tinyshare/py312/config.pyc
tinyshare/py312/device_id.pyc
tinyshare/py312/formula.pyc
tinyshare/py312/general_api_wrapper.pyc
tinyshare/py312/token_utils.pyc
tinyshare/py313/__init__.pyc
tinyshare/py313/cache_utils.pyc
tinyshare/py313/cert_utils.pyc
tinyshare/py313/common_permission.pyc
tinyshare/py313/config.pyc
tinyshare/py313/device_id.pyc
tinyshare/py313/formula.pyc
tinyshare/py313/general_api_wrapper.pyc
tinyshare/py313/token_utils.pyc
tinyshare/py314/__init__.pyc
tinyshare/py314/cache_utils.pyc
tinyshare/py314/cert_utils.pyc
tinyshare/py314/common_permission.pyc
tinyshare/py314/config.pyc
tinyshare/py314/device_id.pyc
tinyshare/py314/formula.pyc
tinyshare/py314/general_api_wrapper.pyc
tinyshare/py314/token_utils.pyc
tinyshare/py38/__init__.pyc
tinyshare/py38/cache_utils.pyc
tinyshare/py38/cert_utils.pyc
tinyshare/py38/common_permission.pyc
tinyshare/py38/config.pyc
tinyshare/py38/device_id.pyc
tinyshare/py38/formula.pyc
tinyshare/py38/general_api_wrapper.pyc
tinyshare/py38/token_utils.pyc
tinyshare/py39/__init__.pyc
tinyshare/py39/cache_utils.pyc
tinyshare/py39/cert_utils.pyc
tinyshare/py39/common_permission.pyc
tinyshare/py39/config.pyc
tinyshare/py39/device_id.pyc
tinyshare/py39/formula.pyc
tinyshare/py39/general_api_wrapper.pyc
tinyshare-0.1026.0.dist-info/licenses/LICENSE
tinyshare-0.1026.0.dist-info/METADATA
tinyshare-0.1026.0.dist-info/WHEEL
tinyshare-0.1026.0.dist-info/top_level.txt
tinyshare-0.1026.0.dist-info/RECORD
